authentication/cli.py
config/__init__.py
config/cli.py
data/__init__.py
data/dataset.py
data/instrument.py
data/investigation.py
data/parcel.py
data/sample.py
data/session.py
invoicing/__init__.py
invoicing/cli.py
invoicing/duration.py
logger_utils/__init__.py
logger_utils/csv_formatter.py
logger_utils/time_formatter.py
minedrac/__init__.py
minedrac/cli.py
minedrac-4.54.1.3.dist-info/licenses/LICENSE.md
performance/__init__.py
performance/cli.py
stats/__init__.py
stats/cli.py
stats/datasets.py
stats/investigation_parameters.py
stats/samples.py
stats/technique/cli.py
stats/technique/technique.py
stats/volume/cli.py
stats/volume/volume.py
tests/invoicing/test_calculate_duration.py
tests/statistics/test_calculate_volume.py
tests/statistics/test_technique.py
tests_integration/test_integration_technique.py
utils/__init__.py
utils/timing.py
utils/units.py
minedrac-4.54.1.3.dist-info/METADATA
minedrac-4.54.1.3.dist-info/WHEEL
minedrac-4.54.1.3.dist-info/entry_points.txt
minedrac-4.54.1.3.dist-info/top_level.txt
minedrac-4.54.1.3.dist-info/RECORD
