Metadata-Version: 2.4
Name: minedrac
Version: 4.54.1.3
Summary: MineDRAC provides a command-line interface to query, analyze, and extract metadata from DRAC.
Project-URL: Homepage, https://icat.gitlab-pages.esrf.fr/MineDRAC
Project-URL: Repository, https://gitlab.esrf.fr/icat/minedrac
Project-URL: Documentation, https://icat.gitlab-pages.esrf.fr/MineDRAC
Requires-Python: >=3.11
License-File: LICENSE.md
Requires-Dist: icat-plus-client
Requires-Dist: typer
Requires-Dist: python-dotenv
Requires-Dist: pandas
Provides-Extra: test
Requires-Dist: pytest; extra == "test"
Requires-Dist: pytest-spec; extra == "test"
Requires-Dist: pytest-dotenv; extra == "test"
Provides-Extra: docs
Requires-Dist: sphinx<9,>=7; extra == "docs"
Requires-Dist: myst-parser<5,>=3; extra == "docs"
Requires-Dist: sphinx-click>=6; extra == "docs"
Provides-Extra: dev
Requires-Dist: typer>=0.20; extra == "dev"
Requires-Dist: pandas>=2.3; extra == "dev"
Requires-Dist: black>=25; extra == "dev"
Requires-Dist: flake8>=4; extra == "dev"
Requires-Dist: ruff; extra == "dev"
Requires-Dist: pytest; extra == "dev"
Requires-Dist: pytest-spec; extra == "dev"
Requires-Dist: pytest-dotenv; extra == "dev"
Dynamic: license-file
